word_document_comment_extractor/__init__.py
word_document_comment_extractor/main.py
word_document_comment_extractor/tools.py
word_document_comment_extractor/utils.py
word_document_comment_extractor_mcp-1.0.2.dist-info/METADATA
word_document_comment_extractor_mcp-1.0.2.dist-info/WHEEL
word_document_comment_extractor_mcp-1.0.2.dist-info/entry_points.txt
word_document_comment_extractor_mcp-1.0.2.dist-info/top_level.txt
word_document_comment_extractor_mcp-1.0.2.dist-info/RECORD
